mvcforge/__init__.py
mvcforge/generator.py
tests/__init__.py
tests/test_generator.py
MVCForge-0.1.dist-info/LICENSE
MVCForge-0.1.dist-info/METADATA
MVCForge-0.1.dist-info/WHEEL
MVCForge-0.1.dist-info/entry_points.txt
MVCForge-0.1.dist-info/top_level.txt
MVCForge-0.1.dist-info/RECORD
