Metadata-Version: 2.1
Name: MVCForge
Version: 0.1
Summary: A simple MVC project structure generator
Home-page: https://github.com/Vicrrs/MVCForge
Author: Victor Roza Souza
Author-email: victorroza22@gmail.com
Classifier: Programming Language :: Python :: 3
Classifier: License :: OSI Approved :: MIT License
Classifier: Operating System :: OS Independent
Requires-Python: >=3.10
License-File: LICENSE
